Metadata-Version: 2.1
Name: astrapiaconsultinghelpers
Version: 0.0.1
Summary: Utility Methods
Home-page: https://github.com/astrapiaconsulting/helpers
Author: Bhavya Kumawat
Author-email: bhavyakumawat99@gmail.com
License: MIT
Platform: UNKNOWN
